setup.py
pycri_spotify.egg-info/PKG-INFO
pycri_spotify.egg-info/SOURCES.txt
pycri_spotify.egg-info/dependency_links.txt
pycri_spotify.egg-info/requires.txt
pycri_spotify.egg-info/top_level.txt
spotify/__init__.py
spotify/spotify.py
spotify/tests.py