Metadata-Version: 1.1
Name: pycri-spotify
Version: 0.1
Summary: Spotify plugin for pycri
Home-page: https://github.com/xintron/pycri-spotify
Author: Marcus Carlsson
Author-email: carlsson.marcus@gmail.com
License: UNKNOWN
Platform: UNKNOWN
Classifier: Development Status :: 2 - Pre-Alpha
Classifier: Environment :: Console
Classifier: Framework :: Twisted
Classifier: Intended Audience :: Developers
Classifier: License :: OSI Approved :: BSD License
Classifier: Operating System :: OS Independent
Classifier: Topic :: Communications :: Chat :: Internet Relay Chat
Provides: pycri_spotify
